{
	"description": "项目配置文件。",
	"packOptions": {
		"ignore": []
	},
	"setting": {
		"urlCheck": true,
		"es6": true,
		"postcss": true,
		"minified": true,
		"newFeature": true
	},
	"compileType": "miniprogram",
	"libVersion": "2.2.1",
	"appid": "wxd066f11915f5efb5",
	"projectname": "cardTwo",
	"isGameTourist": false,
	"condition": {
		"search": {
			"current": -1,
			"list": []
		},
		"conversation": {
			"current": -1,
			"list": []
		},
		"plugin": {
			"current": -1,
			"list": []
		},
		"game": {
			"currentL": -1,
			"list": []
		},
		"miniprogram": {
			"current": 8,
			"list": [
				{
					"id": 0,
					"name": "user",
					"pathName": "pages/user/user",
					"query": ""
				},
				{
					"id": -1,
					"name": "cre",
					"pathName": "pages/credit/credit",
					"query": ""
				},
				{
					"id": -1,
					"name": "merchen",
					"pathName": "pages/merchant/merchant",
					"query": ""
				},
				{
					"id": -1,
					"name": "inex",
					"pathName": "pages/index/index",
					"query": ""
				},
				{
					"id": -1,
					"name": "个人信息",
					"pathName": "pages/userInfor/userInfor",
					"query": ""
				},
				{
					"id": -1,
					"name": "我的积分",
					"pathName": "pages/credit/credit",
					"query": ""
				},
				{
					"id": -1,
					"name": "修改密码",
					"pathName": "pages/password/password",
					"query": ""
				},
				{
					"id": -1,
					"name": "商家个人中心",
					"pathName": "pages/merchant/merchant",
					"query": ""
				},
				{
					"id": -1,
					"name": "我的收入",
					"pathName": "pages/incomRecord/incomRecord"
				}
			]
		}
	}
}